Metadata-Version: 2.1
Name: PromptEHR
Version: 0.0.6
Summary: Sequence patient electronic healthcare record generation with large language models (LLMs) as the neural database.
Home-page: https://github.com/RyanWangZf/PromptEHR
Author: Zifeng Wang
Author-email: zifengw2@illinois.edu
Keywords: synthetic data,healthcare,EHR,deep learning,AI
Classifier: Programming Language :: Python :: 3
Classifier: Programming Language :: Python :: 3.8
Classifier: Programming Language :: Python :: 3.9
Classifier: License :: OSI Approved :: BSD License
Classifier: Operating System :: OS Independent
License-File: LICENSE
Requires-Dist: wget
Requires-Dist: tqdm
Requires-Dist: dill
Requires-Dist: numpy
Requires-Dist: tokenizers (>=0.12.1)
Requires-Dist: torch (>=1.11.0)
Requires-Dist: transformers (>=4.19.0)
